Molara-0.1.1.dist-info/METADATA
Molara-0.1.1.dist-info/RECORD
Molara-0.1.1.dist-info/top_level.txt
Molara-0.1.1.dist-info/WHEEL
Molara-0.1.1.dist-info/LICENSE
Molara-0.1.1.dist-info/entry_points.txt
molara/MolaraLogo.png
molara/py.typed
molara/__init__.py
molara/__main__.py
molara/gui/export_image_dialog.py
molara/gui/structure_widget.py
molara/gui/surface_3d_dialog.py
molara/gui/supercell_dialog.py
molara/gui/measuring_tool_dialog.py
molara/gui/__init__.py
molara/gui/crystal_dialog.py
molara/gui/mos_dialog.py
molara/gui/structure_customizer_dialog.py
molara/gui/surface_3d.py
molara/gui/normalization_dialog.py
molara/gui/builder.py
molara/gui/trajectory_dialog.py
molara/gui/main_window.py
molara/gui/layouts/ui_trajectory.py
molara/gui/layouts/ui_mos_dialog.py
molara/gui/layouts/ui_measuring_tool.py
molara/gui/layouts/ui_supercell_dialog.py
molara/gui/layouts/ui_virtual_rendering_window.py
molara/gui/layouts/ui_export_image_dialog.py
molara/gui/layouts/__init__.py
molara/gui/layouts/ui_form.py
molara/gui/layouts/ui_structure_customizer.py
molara/gui/layouts/ui_builder.py
molara/gui/layouts/ui_surface_3d_dialog.py
molara/gui/layouts/ui_crystalstructure_dialog.py
molara/gui/layouts/ui_normalization_dialog.py
molara/eval/mos.pyx
molara/eval/mos.c
molara/eval/generate_voxel_grid.pyx
molara/eval/voxel_grid.py
molara/eval/trianglelookuptable.py
molara/eval/marchingsquares.pyx
molara/eval/marchingsquares.cpython-311-x86_64-linux-gnu.so
molara/eval/generate_voxel_grid.c
molara/eval/populationanalysis.py
molara/eval/__init__.py
molara/eval/generate_voxel_grid.cpython-311-x86_64-linux-gnu.so
molara/eval/aos.pyx
molara/eval/aos.pxd
molara/eval/marchingcubes.c
molara/eval/aos.c
molara/eval/marchingcubes.pyx
molara/eval/marchingcubes.cpython-311-x86_64-linux-gnu.so
molara/eval/marchingsquares.c
molara/eval/aos.cpython-311-x86_64-linux-gnu.so
molara/eval/mos.pxd
molara/eval/mos.cpython-311-x86_64-linux-gnu.so
molara/settings/structure/Default.json
molara/tools/raycasting.c
molara/tools/__init__.py
molara/tools/mathtools.cpython-311-x86_64-linux-gnu.so
molara/tools/mathtools.c
molara/tools/mathtools.pyx
