Metadata-Version: 2.2
Name: Molara
Version: 0.1.1
Summary: A visualisation tool for chemical structures.
Author: Gereon Feldmann
Author-email: Michel Heinz <michel.heinz@rwth-aachen.de>, Adrian Usler <adrian.usler@rwth-aachen.de>, Alexander Bonkowski <alexander.bonkowski@rwth-aachen.de>
Maintainer: Michel Heinz, Gereon Feldmann, Adrian Usler, Alexander Bonkowski
License:                     GNU GENERAL PUBLIC LICENSE
Project-URL: Repo, https://github.com/Molara-Lab/Molara
Keywords: analysis, science, structure, visualisation
Classifier: Development Status :: 2 - Pre-Alpha
Classifier: Intended Audience :: Science/Research
Classifier: License :: OSI Approved :: GNU General Public License v3 (GPLv3)
Classifier: Operating System :: OS Independent
Classifier: Programming Language :: Python :: 3
Classifier: Programming Language :: Python :: 3.10
Classifier: Programming Language :: Python :: 3.11
Classifier: Programming Language :: Python :: 3.12
Classifier: Topic :: Scientific/Engineering :: Chemistry
Classifier: Topic :: Scientific/Engineering :: Physics
Classifier: Topic :: Scientific/Engineering :: Visualization
Classifier: Topic :: Software Development :: Libraries :: Python Modules
Requires-Python: >=3.10
License-File: LICENSE
License-File: src/molara/Structure/periodic_table_copyright
Requires-Dist: pillow>=10.0.0
Requires-Dist: PyOpenGL>=3.1.6
Requires-Dist: PySide6>=6.3.0
Requires-Dist: matplotlib>=3.6.2
Requires-Dist: numpy>=1.22
Requires-Dist: pyrr>=0.10.3
Requires-Dist: scipy>=1.7.0
Provides-Extra: doc
Requires-Dist: sphinx>=4; extra == "doc"
Requires-Dist: sphinx_rtd_theme>=1; extra == "doc"
Requires-Dist: myst-parser; extra == "doc"
Provides-Extra: tests
Requires-Dist: pytest>=7; extra == "tests"
Requires-Dist: pytest-qt>=4; extra == "tests"
Requires-Dist: pytest-xvfb>=3; extra == "tests"
Requires-Dist: pytest-cov>=5; extra == "tests"
Requires-Dist: pytest-split>=0.8.0; extra == "tests"
Provides-Extra: dev
Requires-Dist: cython; extra == "dev"
Requires-Dist: mypy>=1; extra == "dev"
Requires-Dist: pre-commit>=3; extra == "dev"
Requires-Dist: ruff>=0.5.0; extra == "dev"
Requires-Dist: molara[doc]; extra == "dev"
Provides-Extra: strict
Requires-Dist: PySide6==6.8.1.1; extra == "strict"
Requires-Dist: numpy==2.2.1; extra == "strict"
Requires-Dist: pyrr==0.10.3; extra == "strict"
Requires-Dist: scipy==1.14.1; extra == "strict"
Requires-Dist: cython==3.0.11; extra == "strict"
Provides-Extra: compchem
Requires-Dist: cclib>=1.7; extra == "compchem"
Provides-Extra: crystal
Requires-Dist: pymatgen>=2024; extra == "crystal"
Requires-Dist: ase>=3.23; extra == "crystal"
